cssutils/__init__.py
cssutils/_fetch.py
cssutils/_fetchgae.py
cssutils/codec.py
cssutils/css2productions.py
cssutils/cssproductions.py
cssutils/errorhandler.py
cssutils/helper.py
cssutils/parse.py
cssutils/prodparser.py
cssutils/profiles.py
cssutils/sac.py
cssutils/script.py
cssutils/serialize.py
cssutils/settings.py
cssutils/tokenize2.py
cssutils/util.py
cssutils/css/__init__.py
cssutils/css/colors.py
cssutils/css/csscharsetrule.py
cssutils/css/csscomment.py
cssutils/css/cssfontfacerule.py
cssutils/css/cssimportrule.py
cssutils/css/cssmediarule.py
cssutils/css/cssnamespacerule.py
cssutils/css/csspagerule.py
cssutils/css/cssproperties.py
cssutils/css/cssrule.py
cssutils/css/cssrulelist.py
cssutils/css/cssstyledeclaration.py
cssutils/css/cssstylerule.py
cssutils/css/cssstylesheet.py
cssutils/css/cssunknownrule.py
cssutils/css/cssvalue.py
cssutils/css/cssvariablesdeclaration.py
cssutils/css/cssvariablesrule.py
cssutils/css/marginrule.py
cssutils/css/property.py
cssutils/css/selector.py
cssutils/css/selectorlist.py
cssutils/css/value.py
cssutils/scripts/__init__.py
cssutils/scripts/csscapture.py
cssutils/scripts/csscombine.py
cssutils/scripts/cssparse.py
cssutils/stylesheets/__init__.py
cssutils/stylesheets/medialist.py
cssutils/stylesheets/mediaquery.py
cssutils/stylesheets/stylesheet.py
cssutils/stylesheets/stylesheetlist.py
cssutils/tests/__init__.py
cssutils/tests/basetest.py
cssutils/tests/test_codec.py
cssutils/tests/test_csscharsetrule.py
cssutils/tests/test_csscomment.py
cssutils/tests/test_cssfontfacerule.py
cssutils/tests/test_cssimportrule.py
cssutils/tests/test_cssmediarule.py
cssutils/tests/test_cssnamespacerule.py
cssutils/tests/test_csspagerule.py
cssutils/tests/test_cssproperties.py
cssutils/tests/test_cssrule.py
cssutils/tests/test_cssrulelist.py
cssutils/tests/test_cssstyledeclaration.py
cssutils/tests/test_cssstylerule.py
cssutils/tests/test_cssstylesheet.py
cssutils/tests/test_cssunknownrule.py
cssutils/tests/test_cssutils.py
cssutils-2.11.0.dist-info/COPYING
cssutils-2.11.0.dist-info/COPYING.LESSER
cssutils-2.11.0.dist-info/METADATA
cssutils-2.11.0.dist-info/WHEEL
cssutils-2.11.0.dist-info/entry_points.txt
cssutils-2.11.0.dist-info/top_level.txt
cssutils-2.11.0.dist-info/RECORD
