Metadata-Version: 2.1
Name: cssutils
Version: 2.11.0
Summary: A CSS Cascading Style Sheets library for Python
Author-email: Christof Hoeke <c@cthedot.de>
Maintainer-email: "Jason R. Coombs" <jaraco@jaraco.com>
Project-URL: Homepage, https://github.com/jaraco/cssutils
Keywords: CSS,Cascading Style Sheets,CSSParser,DOM Level 2 Stylesheets,DOM Level 2 CSS
Classifier: Development Status :: 5 - Production/Stable
Classifier: Intended Audience :: Developers
Classifier: License :: OSI Approved :: GNU Library or Lesser General Public License (LGPL)
Classifier: Programming Language :: Python :: 3
Classifier: Programming Language :: Python :: 3 :: Only
Classifier: Topic :: Internet
Classifier: Topic :: Software Development :: Libraries :: Python Modules
Classifier: Topic :: Text Processing :: Markup :: HTML
Requires-Python: >=3.8
License-File: COPYING
License-File: COPYING.LESSER
Provides-Extra: testing
Requires-Dist: pytest!=8.1.*,>=6; extra == "testing"
Requires-Dist: pytest-checkdocs>=2.4; extra == "testing"
Requires-Dist: pytest-cov; extra == "testing"
Requires-Dist: pytest-mypy; extra == "testing"
Requires-Dist: pytest-enabler>=2.2; extra == "testing"
Requires-Dist: pytest-ruff>=0.2.1; extra == "testing"
Requires-Dist: lxml; python_version < "3.11" and extra == "testing"
Requires-Dist: cssselect; extra == "testing"
Requires-Dist: importlib_resources; python_version < "3.9" and extra == "testing"
Requires-Dist: jaraco.test>=5.1; extra == "testing"
Provides-Extra: docs
Requires-Dist: sphinx>=3.5; extra == "docs"
Requires-Dist: jaraco.packaging>=9.3; extra == "docs"
Requires-Dist: rst.linker>=1.9; extra == "docs"
Requires-Dist: furo; extra == "docs"
Requires-Dist: sphinx-lint; extra == "docs"
Requires-Dist: jaraco.tidelift>=1.4; extra == "docs"
